[{
  "_id": {
    "$oid": "64a1bcc0c564132632a17b0d"
  },
  "id": 2,
  "customer_id": 4,
  "deliveryaddress": "Navi Mumbai",
  "orderdate": {
    "$date": "2023-07-02T00:00:00.000Z"
  },
  "status": "ORDERED",
  "invoiceamount": 1200
},{
  "_id": {
    "$oid": "64a1c02d7dab5190c3e07bcd"
  },
  "id": 3,
  "customer_id": 2,
  "deliveryaddress": "Pune",
  "orderdate": {
    "$date": "2023-07-02T00:00:00.000Z"
  },
  "status": "ORDERED",
  "invoiceamount": 2160
},{
  "_id": {
    "$oid": "64a1c2740f0d55db2e993ee3"
  },
  "id": 4,
  "customer_id": 2,
  "deliveryaddress": "Pune",
  "orderdate": {
    "$date": "2023-07-02T00:00:00.000Z"
  },
  "status": "ORDERED",
  "invoiceamount": 420
},{
  "_id": {
    "$oid": "64a1c3495f7c4e55dec055c2"
  },
  "id": 5,
  "customer_id": 4,
  "deliveryaddress": "Navi Mumbai",
  "orderdate": {
    "$date": "2023-07-02T00:00:00.000Z"
  },
  "status": "ORDERED",
  "invoiceamount": 540
},{
  "_id": {
    "$oid": "64a1c3920c751e01631efa5f"
  },
  "id": 6,
  "customer_id": 4,
  "deliveryaddress": "Navi Mumbai",
  "orderdate": {
    "$date": "2023-07-02T00:00:00.000Z"
  },
  "status": "ORDERED",
  "invoiceamount": 500
},{
  "_id": {
    "$oid": "64a1c3b4fd86d2dd89fb6c94"
  },
  "id": 7,
  "customer_id": 4,
  "deliveryaddress": "Navi Mumbai",
  "orderdate": {
    "$date": "2023-07-02T00:00:00.000Z"
  },
  "status": "ORDERED",
  "invoiceamount": 1080
},{
  "_id": {
    "$oid": "64a1c3d54efa17489586fdd8"
  },
  "id": 8,
  "customer_id": 4,
  "deliveryaddress": "Navi Mumbai",
  "orderdate": {
    "$date": "2023-07-02T00:00:00.000Z"
  },
  "status": "ORDERED",
  "invoiceamount": 1080
},{
  "_id": {
    "$oid": "64a1c41c39bf4fa9d4646f90"
  },
  "id": 9,
  "customer_id": 4,
  "deliveryaddress": "Navi Mumbai",
  "orderdate": {
    "$date": "2023-07-02T00:00:00.000Z"
  },
  "status": "DELIVERED",
  "invoiceamount": 1080
},{
  "_id": {
    "$oid": "64b511df747ac03513ff37d1"
  },
  "id": 10,
  "customer_id": 6,
  "deliveryaddress": "some address",
  "orderdate": {
    "$date": "2023-07-17T00:00:00.000Z"
  },
  "status": "ORDERED",
  "invoiceamount": null
},{
  "_id": {
    "$oid": "64b511f8747ac03513ff37d2"
  },
  "id": 11,
  "customer_id": 6,
  "deliveryaddress": "some address",
  "orderdate": {
    "$date": "2023-07-17T00:00:00.000Z"
  },
  "status": "ORDERED",
  "invoiceamount": null
},{
  "_id": {
    "$oid": "64b512027fdf6c7ba06a0f28"
  },
  "id": 12,
  "customer_id": 6,
  "deliveryaddress": "some address",
  "orderdate": {
    "$date": "2023-07-17T00:00:00.000Z"
  },
  "status": "ORDERED",
  "invoiceamount": null
},{
  "_id": {
    "$oid": "64b5157d7fdf6c7ba06a0f29"
  },
  "id": 13,
  "customer_id": 6,
  "deliveryaddress": "some address",
  "orderdate": {
    "$date": "2023-07-17T00:00:00.000Z"
  },
  "status": "ORDERED",
  "invoiceamount": null
},{
  "_id": {
    "$oid": "64b515f6c5734e227d04887a"
  },
  "id": 14,
  "customer_id": 6,
  "deliveryaddress": "some address",
  "orderdate": {
    "$date": "2023-07-17T00:00:00.000Z"
  },
  "status": "ORDERED",
  "invoiceamount": 5220
},{
  "_id": {
    "$oid": "64b51626c5734e227d04887d"
  },
  "id": 15,
  "customer_id": 6,
  "deliveryaddress": "some address",
  "orderdate": {
    "$date": "2023-07-17T00:00:00.000Z"
  },
  "status": "ORDERED",
  "invoiceamount": 5220
},{
  "_id": {
    "$oid": "64b516316b7547d65de7f8b4"
  },
  "id": 16,
  "customer_id": 6,
  "deliveryaddress": "some address",
  "orderdate": {
    "$date": "2023-07-17T00:00:00.000Z"
  },
  "status": "ORDERED",
  "invoiceamount": 5220
},{
  "_id": {
    "$oid": "64b51643fd94a2b4370626c6"
  },
  "id": 17,
  "customer_id": 6,
  "deliveryaddress": "some address",
  "orderdate": {
    "$date": "2023-07-17T00:00:00.000Z"
  },
  "status": "ORDERED",
  "invoiceamount": 5220
},{
  "_id": {
    "$oid": "64b5177ffd94a2b4370626c9"
  },
  "id": 18,
  "customer_id": 6,
  "deliveryaddress": "some address",
  "orderdate": {
    "$date": "2023-07-17T00:00:00.000Z"
  },
  "status": "ORDERED",
  "invoiceamount": 5220
},{
  "_id": {
    "$oid": "64b517a9fd94a2b4370626cc"
  },
  "id": 19,
  "customer_id": 6,
  "deliveryaddress": "some address",
  "orderdate": {
    "$date": "2023-07-17T00:00:00.000Z"
  },
  "status": "ORDERED",
  "invoiceamount": 5220
},{
  "_id": {
    "$oid": "64b517e1fd94a2b4370626cf"
  },
  "id": 20,
  "customer_id": 6,
  "deliveryaddress": "some address",
  "orderdate": {
    "$date": "2023-07-17T00:00:00.000Z"
  },
  "status": "ORDERED",
  "invoiceamount": 5220
},{
  "_id": {
    "$oid": "64b51815fd94a2b4370626d2"
  },
  "id": 21,
  "customer_id": 6,
  "deliveryaddress": "some address",
  "orderdate": {
    "$date": "2023-07-17T00:00:00.000Z"
  },
  "status": "ORDERED",
  "invoiceamount": 5220
},{
  "_id": {
    "$oid": "64b51842fd94a2b4370626d5"
  },
  "id": 22,
  "customer_id": 6,
  "deliveryaddress": "some address",
  "orderdate": {
    "$date": "2023-07-17T00:00:00.000Z"
  },
  "status": "ORDERED",
  "invoiceamount": 5220
},{
  "_id": {
    "$oid": "64b51849fd94a2b4370626d8"
  },
  "id": 23,
  "customer_id": 6,
  "deliveryaddress": "some address",
  "orderdate": {
    "$date": "2023-07-17T00:00:00.000Z"
  },
  "status": "ORDERED",
  "invoiceamount": 5220
},{
  "_id": {
    "$oid": "64b519eefd94a2b4370626db"
  },
  "id": 24,
  "customer_id": 6,
  "deliveryaddress": "some address",
  "orderdate": {
    "$date": "2023-07-17T00:00:00.000Z"
  },
  "status": "ORDERED",
  "invoiceamount": 5220
},{
  "_id": {
    "$oid": "64b51a03fd94a2b4370626de"
  },
  "id": 25,
  "customer_id": 6,
  "deliveryaddress": "some address",
  "orderdate": {
    "$date": "2023-07-17T00:00:00.000Z"
  },
  "status": "ORDERED",
  "invoiceamount": 5220
},{
  "_id": {
    "$oid": "64b51a21fd94a2b4370626e1"
  },
  "id": 26,
  "customer_id": 6,
  "deliveryaddress": "some address",
  "orderdate": {
    "$date": "2023-07-17T00:00:00.000Z"
  },
  "status": "ORDERED",
  "invoiceamount": 5220
},{
  "_id": {
    "$oid": "64b51b24fd94a2b4370626e4"
  },
  "id": 27,
  "customer_id": 6,
  "deliveryaddress": "some address",
  "orderdate": {
    "$date": "2023-07-17T00:00:00.000Z"
  },
  "status": "ORDERED",
  "invoiceamount": 5220
},{
  "_id": {
    "$oid": "64b51b2af71df6e6636e8ac7"
  },
  "id": 28,
  "customer_id": 6,
  "deliveryaddress": "some address",
  "orderdate": {
    "$date": "2023-07-17T00:00:00.000Z"
  },
  "status": "ORDERED",
  "invoiceamount": 5220
}]